python_introspect/__init__.py
python_introspect/enableable.py
python_introspect/exceptions.py
python_introspect/signature_analyzer.py
python_introspect/unified_parameter_analyzer.py
python_introspect-0.1.4.dist-info/licenses/LICENSE
python_introspect-0.1.4.dist-info/METADATA
python_introspect-0.1.4.dist-info/WHEEL
python_introspect-0.1.4.dist-info/top_level.txt
python_introspect-0.1.4.dist-info/RECORD
