Metadata-Version: 2.4
Name: python-introspect
Version: 0.1.4
Summary: Pure Python introspection toolkit for function signatures, dataclasses, and type hints
Author-email: Tristan Simas <tristan.simas@mail.mcgill.ca>
License: MIT
Project-URL: Homepage, https://github.com/OpenHCSDev/python-introspect
Project-URL: Repository, https://github.com/OpenHCSDev/python-introspect
Project-URL: Issues, https://github.com/OpenHCSDev/python-introspect/issues
Keywords: introspection,reflection,signature,dataclass,type-hints,docstring
Classifier: Development Status :: 3 - Alpha
Classifier: Intended Audience :: Developers
Classifier: License :: OSI Approved :: MIT License
Classifier: Programming Language :: Python :: 3
Classifier: Programming Language :: Python :: 3.9
Classifier: Programming Language :: Python :: 3.10
Classifier: Programming Language :: Python :: 3.11
Classifier: Programming Language :: Python :: 3.12
Classifier: Topic :: Software Development :: Libraries :: Python Modules
Classifier: Topic :: Utilities
Requires-Python: >=3.9
License-File: LICENSE
Provides-Extra: dev
Requires-Dist: pytest>=7.0; extra == "dev"
Requires-Dist: pytest-cov>=4.0; extra == "dev"
Requires-Dist: ruff>=0.1.0; extra == "dev"
Requires-Dist: black>=23.0; extra == "dev"
Requires-Dist: mypy>=1.0; extra == "dev"
Provides-Extra: docs
Requires-Dist: sphinx>=7.0.0; extra == "docs"
Requires-Dist: sphinx-rtd-theme>=2.0.0; extra == "docs"
Requires-Dist: sphinx-autodoc-typehints>=1.24.0; extra == "docs"
Dynamic: license-file
